sim/sipo.v
// ---------------------------------------------
// 4-bit Serial-In Parallel-Out (SIPO) Register
// ---------------------------------------------
module sipo #(
    parameter WIDTH = 4              // Parallel width (default 4)
)(
    input  logic              clk,        // Clock
    input  logic              rst_n,      // Active-low reset
    input  logic              serial_in,  // Serial input bit
    output logic [WIDTH-1:0]  q           // Parallel output
);

    always_ff @(posedge clk or negedge rst_n) begin
        if (!rst_n)
            q <= '0;                              // Clear all bits on reset
        else
            q <= {q[WIDTH-2:0], serial_in};       // Shift-left; bring in serial_in
    end

endmodule

src/tb_sipo.v
// ---------------------------------------------
// Testbench for 4-bit SIPO Shift Register
// ---------------------------------------------
`timescale 1ns/1ps

module tb_sipo;

    // Parameters
    localparam WIDTH = 4;

    // Testbench signals
    logic clk;
    logic rst_n;
    logic serial_in;
    logic [WIDTH-1:0] q;

    // DUT Instantiation
    sipo #(.WIDTH(WIDTH)) dut (
        .clk(clk),
        .rst_n(rst_n),
        .serial_in(serial_in),
        .q(q)
    );

    // Clock Generation: 10ns period
    always #5 clk = ~clk;

    // Stimulus
    initial begin
        $dumpfile("sipo.vcd");   // waveform file
        $dumpvars(0, tb_sipo);

        // Init
        clk = 0;
        rst_n = 0;
        serial_in = 0;

        // Reset
        #10;
        rst_n = 1;

        // Shift sequence: 1,0,1,1
        serial_in = 1; #10;
        serial_in = 0; #10;
        serial_in = 1; #10;
        serial_in = 1; #10;

        // Few more cycles
        serial_in = 0; #40;

        $finish;
    end

endmodule

src/sipo.vcd
$date
	Thu Aug 21 00:17:00 2025
$end
$version
	Icarus Verilog
$end
$timescale
	1ps
$end
$scope module tb_sipo $end
$var wire 4 ! q [3:0] $end
$var parameter 32 " WIDTH $end
$var reg 1 # clk $end
$var reg 1 $ rst_n $end
$var reg 1 % serial_in $end
$scope module dut $end
$var wire 1 # clk $end
$var wire 1 $ rst_n $end
$var wire 1 % serial_in $end
$var parameter 32 & WIDTH $end
$var reg 4 ' q [3:0] $end
$upscope $end
$upscope $end
$enddefinitions $end
$comment Show the parameter values. $end
$dumpall
b100 &
b100 "
$end
#0
$dumpvars
b0 '
0%
0$
0#
b0 !
$end
#5000
1#
#10000
0#
1%
1$
#15000
b1 !
b1 '
1#
#20000
0#
0%
#25000
b10 !
b10 '
1#
#30000
0#
1%
#35000
b101 !
b101 '
1#
#40000
0#
#45000
b1011 !
b1011 '
1#
#50000
0#
0%
#55000
b110 !
b110 '
1#
#60000
0#
#65000
b1100 !
b1100 '
1#
#70000
0#
#75000
b1000 !
b1000 '
1#
#80000
0#
#85000
b0 !
b0 '
1#
